Metadata-Version: 2.1
Name: example-package-caichu-pypi
Version: 1.0.1
Summary: A useful module
Home-page: https://github.com/pypa/sampleproject
Author: Cai Chu
Author-email: caichu.fh@antgroup.com
License: UNKNOWN
Project-URL: Bug Tracker, https://github.com/pypa/sampleproject/issues
Platform: any
Classifier: Programming Language :: Python :: 3
Classifier: License :: OSI Approved :: MIT License
Classifier: Operating System :: OS Independent
Requires-Python: >=3.6
License-File: LICENSE
Requires-Dist: wheel
Requires-Dist: bar
